w0/__init__.py
wrng-0.0.0.dist-info/METADATA
wrng-0.0.0.dist-info/WHEEL
wrng-0.0.0.dist-info/top_level.txt
wrng-0.0.0.dist-info/RECORD
