Metadata-Version: 2.1
Name: wrng
Version: 0.0.0
Summary: Default template for PDM package
Author-email: w0rng <me@w0rng.ru>
License: MIT
Requires-Python: ==3.12.*
